anl_agents/__init__.py
anl_agents/__main__.py
anl_agents/agents.py
anl_agents/anl2024/__init__.py
anl_agents/anl2024/antiagents/__init__.py
anl_agents/anl2024/antiagents/antiagent.py
anl_agents/anl2024/antiagents/report.pdf
anl_agents/anl2024/antiagents/requirements.txt
anl_agents/anl2024/carc/__init__.py
anl_agents/anl2024/carc/carcagent.py
anl_agents/anl2024/carc/report.pdf
anl_agents/anl2024/susumu/README.md
anl_agents/anl2024/susumu/__init__.py
anl_agents/anl2024/susumu/nayesian.py
anl_agents/anl2024/susumu/nayesian2.py
anl_agents/anl2024/susumu/report.pdf
anl_agents/anl2024/susumu/helpers/__init__.py
anl_agents/anl2024/susumu/helpers/example.py
anl_agents/anl2024/susumu/helpers/runner.py
anl_agents/anl2024/takafam/__init__.py
anl_agents/anl2024/takafam/report.pdf
anl_agents/anl2024/takafam/requirements.txt
anl_agents/anl2024/takafam/shochan.py
anl_agents/anl2024/takafam/helpers/__init__.py
anl_agents/anl2024/takafam/helpers/runner.py
anl_agents/anl2024/team_123/__init__.py
anl_agents/anl2024/team_123/base.py
anl_agents/anl2024/team_123/nyan.py
anl_agents/anl2024/team_123/report.pdf
anl_agents/anl2024/team_123/helpers/__init__.py
anl_agents/anl2024/team_123/helpers/example.py
anl_agents/anl2024/team_123/helpers/runner.py
anl_agents/anl2024/team_182/__init__.py
anl_agents/anl2024/team_182/missg.py
anl_agents/anl2024/team_186/__init__.py
anl_agents/anl2024/team_186/ilan.py
anl_agents/anl2024/team_186/myagent.py
anl_agents/anl2024/team_186/report.pdf
anl_agents/anl2024/team_186/helpers/__init__.py
anl_agents/anl2024/team_186/helpers/example.py
anl_agents/anl2024/team_186/helpers/runner.py
anl_agents/anl2024/team_191/README.md
anl_agents/anl2024/team_191/__init__.py
anl_agents/anl2024/team_191/func.py
anl_agents/anl2024/team_191/inegotiator.py
anl_agents/anl2024/team_191/others.py
anl_agents/anl2024/team_191/requirements.txt
anl_agents/anl2024/team_191/helpers/__init__.py
anl_agents/anl2024/team_191/helpers/runner.py
anl_agents/anl2024/team_199/__init__.py
anl_agents-0.1.2.dist-info/METADATA
anl_agents-0.1.2.dist-info/WHEEL
anl_agents-0.1.2.dist-info/top_level.txt
anl_agents-0.1.2.dist-info/RECORD
