Metadata-Version: 2.4
Name: anl-agents
Version: 0.1.2
Summary: Agents submitted to the ANL league of ANAC 2025 since 2024
Author-email: Yasser Mohammad <yasserfarouk@gmail.com>
Classifier: Programming Language :: Python :: 3
Classifier: Programming Language :: Python :: 3.11
Classifier: Programming Language :: Python :: Implementation :: CPython
Requires-Python: ~=3.11.0
Requires-Dist: anl>=0.1.13
Requires-Dist: anl2025>=0.1.6
Requires-Dist: tensorflow
Requires-Dist: torch
Requires-Dist: numpy
Provides-Extra: dev
Requires-Dist: pytest; extra == "dev"
Requires-Dist: hypothesis; extra == "dev"
